{
  "permalink": "/docu-jumadi/blog/About",
  "editUrl": "https://github.com/jumadi-cloud/docu-tutorial/blog/2019-05-30-welcome.md",
  "source": "@site/blog/2019-05-30-welcome.md",
  "title": "About",
  "description": "Saya memiliki pengalaman teknis langsung selama 9 tahun di bidang Supply Chain Management (SCM).",
  "date": "2019-05-30T00:00:00.000Z",
  "formattedDate": "May 30, 2019",
  "tags": [
    {
      "label": "facebook",
      "permalink": "/docu-jumadi/blog/tags/facebook"
    },
    {
      "label": "Work Experience",
      "permalink": "/docu-jumadi/blog/tags/work-experience"
    },
    {
      "label": "Education",
      "permalink": "/docu-jumadi/blog/tags/education"
    }
  ],
  "readingTime": 0.465,
  "truncated": false,
  "nextItem": {
    "title": "Work Experience",
    "permalink": "/docu-jumadi/blog/hello-world"
  }
}